miniscutil/__about__.py
miniscutil/__init__.py
miniscutil/adapt.py
miniscutil/asyncio_helpers.py
miniscutil/config.py
miniscutil/current.py
miniscutil/deep.py
miniscutil/deepeq.py
miniscutil/dictdiff.py
miniscutil/dispatch.py
miniscutil/misc.py
miniscutil/ofdict.py
miniscutil/sum.py
miniscutil/type_util.py
miniscutil/lsp/README.md
miniscutil/lsp/__init__.py
miniscutil/lsp/document.py
miniscutil/lsp/server.py
miniscutil/lsp/types.py
miniscutil/rpc/__init__.py
miniscutil/rpc/extrarpc.py
miniscutil/rpc/io_transport.py
miniscutil/rpc/jsonrpc.py
miniscutil/rpc/starlette_ws_transport.py
miniscutil/rpc/transport.py
miniscutil/rpc/websocket_transport.py
miniscutil-0.2.16.dist-info/METADATA
miniscutil-0.2.16.dist-info/WHEEL
miniscutil-0.2.16.dist-info/licenses/LICENSE.txt
miniscutil-0.2.16.dist-info/RECORD
