Metadata-Version: 2.1
Name: miniscutil
Version: 0.2.16
Project-URL: Documentation, https://github.com/EdAyers/sss/miniscutil#readme
Project-URL: Issues, https://github.com/EdAyers/sss/miniscutil/issues
Project-URL: Source, https://github.com/EdAyers/sss/miniscutil
Author-email: "E.W.Ayers" <contact@edayers.com>
License-Expression: MIT
License-File: LICENSE.txt
Classifier: Development Status :: 4 - Beta
Classifier: Programming Language :: Python
Classifier: Programming Language :: Python :: 3.7
Classifier: Programming Language :: Python :: 3.8
Classifier: Programming Language :: Python :: 3.9
Classifier: Programming Language :: Python :: 3.10
Classifier: Programming Language :: Python :: 3.11
Classifier: Programming Language :: Python :: Implementation :: CPython
Classifier: Programming Language :: Python :: Implementation :: PyPy
Requires-Python: >=3.7
Requires-Dist: pydantic
Requires-Dist: typing-extensions; python_version <= '3.9'
